visvalingamwyatt/__init__.py
visvalingamwyatt/__main__.py
visvalingamwyatt/visvalingamwyatt.py
visvalingamwyatt-0.3.0.dist-info/LICENSE.txt
visvalingamwyatt-0.3.0.dist-info/METADATA
visvalingamwyatt-0.3.0.dist-info/WHEEL
visvalingamwyatt-0.3.0.dist-info/entry_points.txt
visvalingamwyatt-0.3.0.dist-info/top_level.txt
visvalingamwyatt-0.3.0.dist-info/zip-safe
visvalingamwyatt-0.3.0.dist-info/RECORD
