Metadata-Version: 2.1
Name: visvalingamwyatt
Version: 0.3.0
Summary: Simplify geometries with the Visvalingam-Wyatt algorithm
Home-page: https://github.com/fitnr/visvalingamwyatt
Author: fitnr
Author-email: contact@fakeisthenewreal.org
License: MIT
Classifier: Development Status :: 4 - Beta
Classifier: Intended Audience :: Developers
Classifier: License :: OSI Approved :: MIT License
Classifier: Programming Language :: Python :: 3.7
Classifier: Programming Language :: Python :: 3.8
Classifier: Programming Language :: Python :: 3.9
Classifier: Programming Language :: Python :: 3.10
Classifier: Programming Language :: Python :: 3.11
Classifier: Programming Language :: Python :: 3.12
Classifier: Programming Language :: Python :: Implementation :: PyPy
Classifier: Operating System :: OS Independent
License-File: LICENSE.txt
Requires-Dist: numpy>=1.8
Provides-Extra: tests
Requires-Dist: coverage; extra == "tests"
